{"0":{"idUser":"111","0":"111","quantit\u00e9Ajout":"5","1":"5","idMenu":"1","2":"1","nomMenu":"CHAKCHOUKA","3":"CHAKCHOUKA","prixMenu":"60","4":"60","image":"menu1.jpg","5":"menu1.jpg","quantiteMenu":"50","6":"50","texte":"menu1.txt","7":"menu1.txt"},"1":{"idUser":"111","0":"111","quantit\u00e9Ajout":"5","1":"5","idMenu":"3","2":"3","nomMenu":"POULET ROTI","3":"POULET ROTI","prixMenu":"20","4":"20","image":"menu3.jpg","5":"menu3.jpg","quantiteMenu":"100","6":"100","texte":"menu3.txt","7":"menu3.txt"},"2":{"idUser":"111","0":"111","quantit\u00e9Ajout":"5","1":"5","idMenu":"4","2":"4","nomMenu":"SHAWARMA","3":"SHAWARMA","prixMenu":"50","4":"50","image":"menu4.jpg","5":"menu4.jpg","quantiteMenu":"30","6":"30","texte":"menu4.txt","7":"menu4.txt"},"3":{"idUser":"111","0":"111","quantit\u00e9Ajout":"5","1":"5","idMenu":"5","2":"5","nomMenu":"PIRON","3":"PIRON","prixMenu":"100","4":"100","image":"menu5.jpg","5":"menu5.jpg","quantiteMenu":"25","6":"25","texte":"menu5.txt","7":"menu5.txt"},"4":{"idUser":"111","0":"111","quantit\u00e9Ajout":"5","1":"5","idMenu":"8","2":"8","nomMenu":"BEIGNETS","3":"BEIGNETS","prixMenu":"15","4":"15","image":"menu8.jpg","5":"menu8.jpg","quantiteMenu":"40","6":"40","texte":"menu8.txt","7":"menu8.txt"},"5":{"idUser":"111","0":"111","quantit\u00e9Ajout":"5","1":"5","idMenu":"7","2":"7","nomMenu":"ATASSI","3":"ATASSI","prixMenu":"80","4":"80","image":"menu7.jpg","5":"menu7.jpg","quantiteMenu":"40","6":"40","texte":"menu7.txt","7":"menu7.txt"},"6":{"idUser":"111","0":"111","quantit\u00e9Ajout":"5","1":"5","idMenu":"6","2":"6","nomMenu":"ABLO","3":"ABLO","prixMenu":"100","4":"100","image":"menu6.jpg","5":"menu6.jpg","quantiteMenu":"40","6":"40","texte":"menu6.txt","7":"menu6.txt"},"7":{"idUser":"111","0":"111","quantit\u00e9Ajout":"5","1":"5","idMenu":"2","2":"2","nomMenu":"GRILLADES","3":"GRILLADES","prixMenu":"40","4":"40","image":"menu2.jpg","5":"menu2.jpg","quantiteMenu":"5","6":"5","texte":"menu2.txt","7":"menu2.txt"},"total":2325}